setup.py
distributions_alif/Binomialdistribution.py
distributions_alif/Gaussiandistribution.py
distributions_alif/Generaldistribution.py
distributions_alif/__init__.py
distributions_alif.egg-info/PKG-INFO
distributions_alif.egg-info/SOURCES.txt
distributions_alif.egg-info/dependency_links.txt
distributions_alif.egg-info/not-zip-safe
distributions_alif.egg-info/top_level.txt