Metadata-Version: 1.0
Name: distributions-alif
Version: 0.1
Summary: Gaussian distributions
Home-page: UNKNOWN
Author: Alif Ilham Madani
Author-email: alifilhammadani@gmail.com
License: UNKNOWN
Platform: UNKNOWN
